[{"status":"Up to Date","service":"HBO","wanted":true,"id":"73CF1778-B7F5-4C09-B375-7F06290D9999","watched":true,"length":"60","discovered":true,"airdate":"Other","running":true,"name":"Hacks"},{"status":"Up to Date","service":"Disney+","wanted":true,"id":"3BE397E1-539E-4CD2-B3AC-7C07667C0B23","watched":true,"length":"30","discovered":true,"airdate":"Other","running":true,"name":"High School Musical"},{"status":"New Season","service":"Hulu","wanted":true,"id":"B9267A71-F0CA-4622-82C5-7140B4969851","watched":false,"length":"30","discovered":true,"airdate":"Other","running":true,"name":"Killing Eve"},{"status":"Up to Date","service":"HBO","wanted":true,"id":"544C3F09-6AEF-4480-A2EA-5074B707D981","watched":true,"length":"30","discovered":true,"airdate":"Sunday","running":true,"name":"Last Week Tonight"},{"status":"Seen Enough","service":"HBO","wanted":true,"id":"A74C4FC1-7E3E-4A0F-9AB8-B0A4C2D591B8","watched":false,"length":"60","discovered":true,"airdate":"Other","running":true,"name":"Lovecraft Country"},{"status":"Catching Up","service":"HBO","wanted":true,"id":"CAD184EC-093A-45FB-861A-AA861812B2B5","watched":false,"length":"30","discovered":true,"airdate":"Other","running":true,"name":"My Brilliant Friend"},{"status":"Show Ended","service":"HBO","wanted":true,"id":"5EC847ED-DD26-49F3-84EF-18425CB5A024","watched":true,"length":"30","discovered":true,"airdate":"Other","running":true,"name":"Sex and the City"},{"status":"New Season","service":"Amazon","wanted":true,"id":"D3AEB4C4-5F96-4FB1-B9FF-AB0B07DECEB5","watched":false,"length":"60","discovered":true,"airdate":"Other","running":true,"name":"The Underground Railroad"},{"status":"Catching Up","service":"HBO","wanted":true,"id":"D29670E4-6267-461D-84D7-9E1F39CF9B2D","watched":false,"length":"60","discovered":true,"airdate":"Other","running":true,"name":"We Are Who We Are"},{"status":"Needs Watched","service":"FX","wanted":true,"id":"79BC34DF-5EEF-4E69-AAC9-B4C9B52D30E6","watched":false,"length":"60","discovered":true,"airdate":"Other","running":true,"name":"American Horror Story"},{"status":"Needs Watched","service":"Netflix","wanted":true,"id":"400D6EDC-8C7E-4C48-8E29-6386EAFBCEE4","watched":false,"length":"30","discovered":true,"airdate":"Other","running":true,"name":"Arrested Development"},{"status":"Needs Watched","service":"Netflix","wanted":true,"id":"1AA7F647-6E86-4193-AC0F-BCFC2A681FC8","watched":false,"length":"60+","discovered":true,"airdate":"Other","running":true,"name":"Black Mirror"},{"status":"Needs Watched","service":"Amazon","wanted":true,"id":"D6234CE4-849E-4B04-9471-744FC37D4351","watched":false,"length":"30","discovered":false,"airdate":"Other","running":true,"name":"Catastrophe"},{"status":"Needs Watched","service":"Apple TV+","wanted":true,"id":"D7B0E6F0-DBB8-4D3A-8C5D-680D94396E8E","watched":false,"length":"30","discovered":true,"airdate":"Other","running":true,"name":"Dickinson"},{"status":"Needs Watched","service":"Netflix","wanted":true,"id":"6CFD138D-8BC7-4D4D-873F-85BD6011CA97","watched":false,"length":"30","discovered":true,"airdate":"Other","running":true,"name":"Glow"},{"status":"Needs Watched","service":"Netflix","wanted":true,"id":"2C3B4BC6-B35C-45F1-AEA3-C5192811F393","watched":false,"length":"30","discovered":true,"airdate":"Other","running":true,"name":"Grace & Frankie"},{"status":"Needs Watched","service":"Hulu","wanted":true,"id":"1E7BFF81-B7B4-4ABF-9F1E-FFACF1C9803C","watched":false,"length":"30","discovered":true,"airdate":"Other","running":true,"name":"Handmaid's Tale"},{"status":"Needs Watched","service":"Netflix","wanted":true,"id":"5804539B-4D79-493B-BC51-6E5D83174F97","watched":false,"length":"60","discovered":true,"airdate":"Other","running":true,"name":"House of Cards"},{"status":"Needs Watched","service":"Disney+","wanted":true,"id":"3AC689C5-E2CD-42D7-A021-7CB7A7F74FE4","watched":false,"length":"30","discovered":true,"airdate":"Other","running":true,"name":"Mandalorian"},{"status":"Needs Watched","service":"Netflix","wanted":true,"id":"DBE7C939-1C0A-414E-90A0-F81830840FA1","watched":false,"length":"30","discovered":true,"airdate":"Other","running":true,"name":"Maniac"},{"status":"Needs Watched","service":"USA","wanted":true,"id":"CE72A774-FF4B-4910-9D7A-3FBD0D3886AF","watched":false,"length":"30","discovered":true,"airdate":"Other","running":true,"name":"Mr. Robot"},{"status":"Needs Watched","service":"Amazon","wanted":true,"id":"8554DAFA-9424-40D8-957E-90D276D06EB2","watched":false,"length":"30","discovered":true,"airdate":"Other","running":true,"name":"Mrs. Maisel"},{"status":"Needs Watched","service":"Netflix","wanted":true,"id":"D8EACD52-E311-489A-BD0C-537AC06684ED","watched":false,"length":"30","discovered":true,"airdate":"Other","running":true,"name":"Narcos"},{"status":"Needs Watched","service":"Netflix","wanted":true,"id":"E131E1D4-B0D7-4BE3-9F38-DA807AB48FA9","watched":false,"length":"30","discovered":true,"airdate":"Other","running":true,"name":"New Girl"},{"status":"Needs Watched","service":"FX","wanted":true,"id":"36BC6EF7-08BC-49AE-BEE6-874CDED66C5F","watched":false,"length":"30","discovered":false,"airdate":"Other","running":true,"name":"The Americans"},{"status":"Needs Watched","service":"Showtime","wanted":true,"id":"8A5F8697-9B9D-4C8A-AED7-345C450688A5","watched":false,"length":"30","discovered":false,"airdate":"Other","running":true,"name":"The Chi"},{"status":"Needs Watched","service":"Netflix","wanted":true,"id":"5CD77209-3628-4CD7-9C2E-B4364AFD0CF5","watched":false,"length":"30","discovered":true,"airdate":"Other","running":true,"name":"Unbreakable Kimmy Schmidt"},{"status":"Seen Enough","service":"CW","wanted":false,"id":"583D4582-7AF9-49DF-ADAF-FFF452A455CF","watched":false,"length":"30","discovered":true,"airdate":"Other","running":true,"name":"Arrow"},{"status":"Seen Enough","service":"Netflix","wanted":false,"id":"C546983A-0C3E-424B-B942-E72D4B0D8B29","watched":false,"length":"30","discovered":true,"airdate":"Other","running":true,"name":"Defenders"},{"status":"Seen Enough","service":"CW","wanted":false,"id":"BE92D3E2-CE5E-43FC-8589-3446A722AA17","watched":false,"length":"30","discovered":true,"airdate":"Other","running":true,"name":"Flash"},{"status":"Seen Enough","service":"Netflix","wanted":false,"id":"7C47662B-B4C1-4371-A138-D1FC6AB82FD4","watched":false,"length":"30","discovered":true,"airdate":"Other","running":true,"name":"Luke Cage"},{"status":"Seen Enough","service":"CW","wanted":false,"id":"D96A0ABE-B22D-4C5E-964A-9AD90DF65FD9","watched":false,"length":"30","discovered":true,"airdate":"Other","running":true,"name":"Riverdale"},{"status":"Seen Enough","service":"AMC","wanted":false,"id":"2B3B2D42-EF7D-45F6-9321-87A2FB7D4F18","watched":false,"length":"60","discovered":true,"airdate":"Other","running":true,"name":"Walking Dead"},{"status":"Show Ended","service":"HBO","wanted":false,"id":"F3977351-F5E3-4315-B9C6-2E79F47E71A1","watched":true,"length":"60","discovered":true,"airdate":"Other","running":false,"name":"Big Little Lies"},{"status":"Show Ended","service":"Amazon","wanted":false,"id":"ED50AAC2-63EA-4A20-AA44-D37D76F4B652","watched":true,"length":"30","discovered":true,"airdate":"Other","running":false,"name":"Fleabag"},{"status":"Show Ended","service":"HBO","wanted":false,"id":"C1B53233-54B7-4DA9-8FE4-5D1E2D032749","watched":true,"length":"60","discovered":true,"airdate":"Other","running":false,"name":"Game of Thrones"},{"status":"Show Ended","service":"NBC","wanted":false,"id":"538A3EB5-0D89-4C3D-B282-C9F84F7AAC03","watched":true,"length":"30","discovered":true,"airdate":"Other","running":false,"name":"Good Place"},{"status":"Show Ended","service":"Netflix","wanted":false,"id":"43E3152C-9695-478F-A9C6-33C62AD64006","watched":true,"length":"30","discovered":true,"airdate":"Other","running":false,"name":"Hollywood"},{"status":"Show Ended","service":"HBO","wanted":false,"id":"DC24564F-4D28-4147-B53C-4DCA2DF8901C","watched":true,"length":"30","discovered":true,"airdate":"Other","running":false,"name":"I May Destroy You"},{"status":"Show Ended","service":"HBO","wanted":false,"id":"F224C1DB-2337-4D06-AFC0-B725CDA54645","watched":true,"length":"30","discovered":true,"airdate":"Other","running":false,"name":"Looking"},{"status":"Show Ended","service":"HBO","wanted":false,"id":"F3B023AC-644D-409E-8BD2-04CA0D4214D7","watched":true,"length":"30","discovered":true,"airdate":"Other","running":false,"name":"Mare of Easttown"},{"status":"Show Ended","service":"Netflix","wanted":false,"id":"B985FF23-849B-47CB-92AB-8040317255B8","watched":true,"length":"30","discovered":true,"airdate":"Other","running":false,"name":"Master of None"},{"status":"Show Ended","service":"Netflix","wanted":false,"id":"0F478901-9826-4AC4-B49B-CE6EEB5EC4C7","watched":true,"length":"30","discovered":true,"airdate":"Other","running":false,"name":"Mindhunter"},{"status":"Show Ended","service":"Hulu","wanted":false,"id":"1A09C626-0911-4F2D-AE94-4A1520341053","watched":true,"length":"30","discovered":true,"airdate":"Other","running":false,"name":"Normal People"},{"status":"Show Ended","service":"Viceland","wanted":false,"id":"485AAD9E-7725-4C5B-888E-199F52332406","watched":true,"length":"30","discovered":true,"airdate":"Other","running":false,"name":"Nuts and Bolts"},{"status":"Show Ended","service":"NBC","wanted":false,"id":"7A504A93-2C39-41E9-8FB2-6ACE38B752AB","watched":true,"length":"30","discovered":true,"airdate":"Other","running":false,"name":"Parks and Rec"},{"status":"Show Ended","service":"HBO","wanted":false,"id":"C1D28559-50CD-4D3D-AF09-3DD94D2395D6","watched":true,"length":"30","discovered":true,"airdate":"Other","running":false,"name":"RUN"},{"status":"Show Ended","service":"Netflix","wanted":false,"id":"C70CB8CC-F600-49D4-B9B0-EC0538414236","watched":true,"length":"30","discovered":true,"airdate":"Other","running":false,"name":"Schitts Creek"},{"status":"Show Ended","service":"HBO","wanted":false,"id":"DD7F04D9-5BE1-483E-8DA8-29F4759AC613","watched":true,"length":"30","discovered":true,"airdate":"Other","running":false,"name":"Silicon Valley"},{"status":"Show Ended","service":"NBC","wanted":false,"id":"A2CBB701-73BF-424E-9989-FE101FE7D4B6","watched":true,"length":"30","discovered":true,"airdate":"Other","running":false,"name":"The Office"},{"status":"Show Ended","service":"HBO","wanted":false,"id":"7D363364-6E17-4175-A1CF-91A41B8E1537","watched":true,"length":"30","discovered":true,"airdate":"Other","running":false,"name":"Veep"},{"status":"Show Ended","service":"Disney+","wanted":false,"id":"B0626BA2-2A3B-4107-B88B-124A61318289","watched":true,"length":"30","discovered":true,"airdate":"Other","running":false,"name":"Wandavision"},{"status":"Show Ended","service":"HBO","wanted":false,"id":"139CD224-DB9A-47C5-8A1A-F850F8F94B3B","watched":true,"length":"60","discovered":true,"airdate":"Other","running":false,"name":"Watchmen"},{"status":"New Season","service":"FX","wanted":true,"id":"82E4D2D6-0B5F-44D7-9D33-2CC71436E73F","watched":true,"length":"60","discovered":true,"airdate":"Tuesday","running":true,"name":"American Crime Story"},{"status":"Up to Date","service":"ABC","wanted":true,"id":"8E22BF6C-C675-4EE7-94D1-251580781E3A","watched":true,"length":"30-60","discovered":true,"airdate":"Other","running":true,"name":"American Idol"},{"status":"Currently Airing","service":"FX","wanted":true,"id":"1166CF85-910A-4644-AECE-5CE2AAE79254","watched":true,"length":"60","discovered":true,"airdate":"Thursday","running":true,"name":"Atlanta"},{"status":"Currently Airing","service":"HBO","wanted":true,"id":"E8BAF36F-ABFB-412F-B8F5-8DEBEDEA5EF0","watched":true,"length":"30","discovered":true,"airdate":"Sunday","running":true,"name":"Barry"},{"status":"Up to Date","service":"Netflix","wanted":true,"id":"C145711E-9E57-4E0B-8E0B-E97BD7905FB7","watched":true,"length":"30","discovered":true,"airdate":"Other","running":true,"name":"Bodyguard"},{"status":"Up to Date","service":"Netflix","wanted":true,"id":"616F2E78-6AA0-44FF-968D-649E26C265C5","watched":true,"length":"30","discovered":true,"airdate":"Other","running":true,"name":"Dead to Me"},{"status":"New Season","service":"Netflix","wanted":true,"id":"920506D0-85CC-438E-9AF9-34BA84B8BC08","watched":true,"length":"60","discovered":true,"airdate":"Other","running":true,"name":"Dear White People"},{"status":"Up to Date","service":"Netflix","wanted":true,"id":"58A22592-4DD6-4D83-A972-62FA9356D769","watched":true,"length":"60","discovered":true,"airdate":"Other","running":true,"name":"Elite"},{"status":"Up to Date","service":"Netflix","wanted":true,"id":"7D8F760A-3AAA-4298-BFED-DC5BFF64D18F","watched":true,"length":"30","discovered":true,"airdate":"Other","running":true,"name":"Emily in Paris"},{"status":"Up to Date","service":"Netflix","wanted":true,"id":"FC0AEE86-5DA7-4646-92A0-F59639ECE91C","watched":true,"length":"30","discovered":true,"airdate":"Other","running":true,"name":"End of the Fucking World"},{"status":"Up to Date","service":"HBO","wanted":true,"id":"52E08FCD-A935-4C58-A831-6BCA960B5C4C","watched":true,"length":"60","discovered":true,"airdate":"Sunday","running":true,"name":"Euphoria"},{"status":"Up to Date","service":"Disney+","wanted":true,"id":"BE5FDE18-23B6-4FD1-AD51-77AFA883C531","watched":true,"length":"30","discovered":true,"airdate":"Other","running":true,"name":"Falcon and the Winter Soldier"},{"status":"Currently Airing","service":"HBO","wanted":true,"id":"BF9BAAEB-80BC-464B-B6CE-EB0E52FFFBFC","watched":true,"length":"30-60","discovered":true,"airdate":"Thursday","running":true,"name":"Flight Attendant"},{"status":"Up to Date","service":"HBO","wanted":true,"id":"E63DC37E-3BA2-4272-9361-1625C4BB66B2","watched":true,"length":"60","discovered":true,"airdate":"Wednesday","running":true,"name":"Hard Knocks"},{"status":"Up to Date","service":"HBO","wanted":true,"id":"B26CD90B-0CFC-4E5E-BEEE-3A024C32969D","watched":true,"length":"30","discovered":true,"airdate":"Friday","running":true,"name":"How to With John Wilson"},{"status":"Up to Date","service":"HBO","wanted":true,"id":"77449F8D-D8BA-420D-83D5-4C8E2385D34B","watched":true,"length":"30","discovered":true,"airdate":"Other","running":true,"name":"Industry"},{"status":"Show Ended","service":"HBO","wanted":true,"id":"954C589B-4BEB-4FE1-9AF3-DDE12FEB6928","watched":true,"length":"30-60","discovered":true,"airdate":"Sunday","running":true,"name":"Insecure"},{"status":"New Season","service":"Netflix","wanted":true,"id":"62DF811D-F555-4282-8B47-3011752BC2BB","watched":true,"length":"60","discovered":true,"airdate":"Other","running":true,"name":"La Casa de Papel"},{"status":"Up to Date","service":"Hulu","wanted":true,"id":"61C56D11-1920-4848-BB63-CE51C7C2261A","watched":true,"length":"30","discovered":true,"airdate":"Other","running":true,"name":"Love Victor"},{"status":"Up to Date","service":"Netflix","wanted":true,"id":"43B223B0-D956-4071-A484-ED16E8102C35","watched":true,"length":"30","discovered":true,"airdate":"Other","running":true,"name":"Lupin"},{"status":"Up to Date","service":"Netflix","wanted":true,"id":"7E771F69-05A5-4E74-B098-A19A70C523AB","watched":true,"length":"30","discovered":true,"airdate":"Other","running":true,"name":"Never Have I Ever"},{"status":"Show Ended","service":"Netflix","wanted":true,"id":"6752DC3F-4B59-4F6C-8967-743E112D5182","watched":true,"length":"30","discovered":true,"airdate":"Other","running":true,"name":"On My Block"},{"status":"Up to Date","service":"Netflix","wanted":true,"id":"F99733F5-ED60-45F9-A1FF-2C12B1609719","watched":true,"length":"30","discovered":true,"airdate":"Other","running":true,"name":"Pose"},{"status":"Up to Date","service":"Netflix","wanted":true,"id":"9E89B173-59AB-4544-B2BE-26AAC80FEA45","watched":true,"length":"30","discovered":true,"airdate":"Other","running":true,"name":"Queer Eye"},{"status":"Up to Date","service":"Netflix","wanted":true,"id":"2E7BDB42-7946-4301-9E79-2B0BA6B23A1C","watched":true,"length":"30","discovered":true,"airdate":"Other","running":true,"name":"Russian Doll"},{"status":"Show Ended","service":"HBO","wanted":true,"id":"A82AC11A-004F-4457-8DA5-B8BF3EFFD193","watched":true,"length":"30","discovered":true,"airdate":"Other","running":true,"name":"Search Party"},{"status":"Up to Date","service":"Netflix","wanted":true,"id":"D1DBB203-6175-4E96-86E7-0BFDCE309578","watched":true,"length":"60","discovered":true,"airdate":"Other","running":true,"name":"Sex Education"},{"status":"Up to Date","service":"Netflix","wanted":true,"id":"F00DC2BD-002A-4A58-AA63-6B78690110DD","watched":true,"length":"30","discovered":true,"airdate":"Other","running":true,"name":"Stranger Things"},{"status":"Up to Date","service":"HBO","wanted":true,"id":"BA848AF1-9531-421A-BDA8-F25FC623D637","watched":true,"length":"60","discovered":true,"airdate":"Sunday","running":true,"name":"Succession"},{"status":"Up to Date","service":"Apple TV+","wanted":true,"id":"4824C640-5E3F-4C93-B474-6AC8B675841C","watched":true,"length":"30","discovered":true,"airdate":"Friday","running":true,"name":"Ted Lasso"},{"status":"Up to Date","service":"Netflix","wanted":true,"id":"AF1665FE-C95A-455D-9AE0-0E453DF7AB94","watched":true,"length":"30","discovered":true,"airdate":"Other","running":true,"name":"The Circle"},{"status":"Up to Date","service":"Netflix","wanted":true,"id":"87ABDD85-7FF3-4738-AB76-34691E801239","watched":true,"length":"60","discovered":true,"airdate":"Other","running":true,"name":"The Crown"},{"status":"Up to Date","service":"Netflix","wanted":true,"id":"572B2C49-C2BC-4264-A987-8A5B51D77CE7","watched":true,"length":"30-60","discovered":true,"airdate":"Other","running":true,"name":"The Politician"},{"status":"Up to Date","service":"Netflix","wanted":true,"id":"AF8034CE-53BB-4517-A5FE-AFBC94C26C6B","watched":true,"length":"30","discovered":true,"airdate":"Other","running":true,"name":"You"},{"status":"Up to Date","service":"Amazon","wanted":true,"id":"B1FFDA12-1779-4CCE-8ED9-487A91D5F6BC","watched":true,"length":"30","discovered":true,"airdate":"Other","running":true,"name":"Modern Love"},{"status":"Up to Date","service":"Netflix","wanted":true,"id":"2F6CB185-477E-4116-AAE8-24CAA7338C11","watched":true,"length":"30","discovered":true,"airdate":"Other","running":true,"name":"The Chair"},{"status":"Up to Date","service":"Netflix","wanted":true,"id":"25617D35-4E50-43B9-828F-188D5C7432A8","watched":true,"length":"30","discovered":true,"airdate":"Other","running":true,"name":"Formula 1: Drive to Survive"},{"status":"Up to Date","service":"Netflix","wanted":true,"id":"74BD057C-DC70-4EDC-83D4-018E0E266686","watched":true,"length":"30","discovered":true,"airdate":"Other","running":true,"name":"I Think You Should Leave with Tim Robinson"},{"status":"Up to Date","service":"HBO","wanted":true,"id":"76FA69EC-2F79-4AEC-83C4-D9BB9F81E759","watched":true,"length":"60","discovered":true,"airdate":"Thursday","running":true,"name":"Gossip Girl (Reboot)"},{"status":"Needs Watched","service":"HBO","wanted":true,"id":"1C4EAD44-1480-4318-9C4C-420AD4CCA9F9","watched":true,"length":"30","discovered":true,"airdate":"Other","running":true,"name":"Gossip Girl (Original)"},{"status":"Up to Date","service":"HBO","wanted":true,"id":"31CA53AE-5CB3-44E2-9C7D-A5DFD2DB22E6","watched":true,"length":"60","discovered":true,"airdate":"Other","running":true,"name":"The White Lotus"},{"status":"Show Ended","service":"Netflix","wanted":true,"id":"83D78CE4-B511-4380-93EF-3AAD62637BF2","watched":true,"length":"60","discovered":true,"airdate":"Other","running":true,"name":"The Queen's Gambit"},{"status":"Show Ended","service":"Netflix","wanted":true,"id":"A6F6CE12-CF1F-447D-BC4E-4279E64B53D7","watched":true,"length":"30","discovered":true,"airdate":"Other","running":true,"name":"Crashing"},{"status":"Up to Date","service":"Netflix","wanted":true,"id":"3AFFF0B3-9F46-45CD-A68C-9FB63460CF33","watched":true,"length":"30","discovered":true,"airdate":"Other","running":true,"name":"Derry Girls"},{"status":"Up to Date","service":"Hulu","wanted":true,"id":"155B39CD-EF29-496E-BBFF-89968847E7C8","watched":true,"length":"30","discovered":true,"airdate":"Tuesday","running":true,"name":"Only Murders in the Building"},{"status":"Needs Watched","service":"HBO","wanted":true,"id":"EBA77B2A-491F-4B0B-AFCA-A6D6783B5D21","watched":false,"length":"60","discovered":true,"airdate":"Sunday","running":true,"name":"Scenes from a Marriage"},{"status":"Currently Watching","service":"Netflix","wanted":true,"id":"B186F126-F226-4752-88FF-F63967D2D9BD","watched":false,"length":"60","discovered":true,"airdate":"Other","running":true,"name":"Squid Game"},{"status":"Up to Date","service":"HBO","wanted":true,"id":"87F528E4-66B4-410B-8045-19EDECA48FBE","watched":true,"length":"30","discovered":true,"airdate":"Thursday","running":true,"name":"Love Life"},{"status":"Up to Date","service":"HBO","wanted":true,"id":"2D312BD7-AA48-4950-B3FA-86611E0F7ECC","watched":true,"length":"30","discovered":true,"airdate":"Other","running":true,"name":"The Other Two"},{"status":"Show Ended","service":"Apple TV+","wanted":true,"id":"D5D8E1CC-1365-4B9B-B23B-7FDA437A98F0","watched":true,"length":"30","discovered":true,"airdate":"Friday","running":true,"name":"The Shrink Next Door"},{"status":"Up to Date","service":"HBO","wanted":true,"id":"B955C9FE-0365-4325-BE9D-7C39412FCF4D","watched":true,"length":"30","discovered":true,"airdate":"Thursday","running":true,"name":"The Sex Lives of College Girls"},{"status":"Up to Date","service":"Disney+","wanted":true,"id":"230EC9CD-F824-43E5-9442-DB2D8383D5D3","watched":true,"length":"30-60","discovered":true,"airdate":"Wednesday","running":true,"name":"Hawkeye"},{"status":"Show Ended","service":"HBO","wanted":true,"id":"01BB2C15-0BE6-4EAB-A14E-987591143053","watched":true,"length":"60","discovered":true,"airdate":"Monday","running":true,"name":"Landscapers"},{"status":"Up to Date","service":"HBO","wanted":true,"id":"67EF8EC2-DF73-4E6C-8AD6-0BF62D9CF063","watched":true,"length":"30-60","discovered":true,"airdate":"Thursday","running":true,"name":"And Just Like That…"},{"status":"Up to Date","service":"ABC","wanted":true,"id":"F365C052-F142-46BA-B781-173E841386CA","watched":true,"length":"30","discovered":true,"airdate":"Tuesday","running":true,"name":"Abbott Elementary"},{"status":"Currently Airing","service":"HBO","wanted":true,"id":"48A703B2-AA07-437C-9A61-F07906BB6048","watched":false,"length":"60","discovered":true,"airdate":"Monday","running":true,"name":"The Gilded Age"},{"status":"Up to Date","service":"Netflix","wanted":true,"id":"BABB3464-6DAC-45EB-95B2-7D76F1D8036B","watched":true,"length":"30","discovered":true,"airdate":"Other","running":true,"name":"The Woman in the House Across the Street from the Girl in the Window"},{"status":"Up to Date","service":"Apple TV+","wanted":true,"id":"DB89440D-C462-4668-AF50-76A9A54F658C","watched":true,"length":"30-60","discovered":true,"airdate":"Friday","running":true,"name":"The Afterparty"},{"status":"Catching Up","service":"Showtime","wanted":true,"id":"C257EB65-2CEA-46BA-B00B-A0A428AABF4A","watched":true,"length":"30","discovered":true,"airdate":"Other","running":true,"name":"Ziwe"},{"status":"Show Ended","service":"Hulu","wanted":true,"id":"214362C5-E008-4F35-9E11-AC6409F88E92","watched":true,"length":"30-60","discovered":true,"airdate":"Thursday","running":true,"name":"The Dropout"},{"status":"Up to Date","service":"Apple TV+","wanted":true,"id":"BB6A72AE-CFF2-41CC-8E6B-609633A25746","watched":true,"length":"60","discovered":true,"airdate":"Friday","running":true,"name":"Severance"},{"status":"Currently Airing","service":"NBC","wanted":true,"id":"CE807072-DB89-402D-9383-9ABA3EE09C75","watched":true,"length":"60","discovered":true,"airdate":"Saturday","running":true,"name":"Saturday Night Live"},{"status":"Needs Watched","service":"Disney+","wanted":true,"id":"2DDBE856-99D4-45FE-AE98-C3BFB8225BB1","watched":false,"length":"<30","discovered":true,"airdate":"Other","running":true,"name":"The Book of Boba Fett"},{"status":"Show Ended","service":"HBO","wanted":true,"id":"FCDCD3D6-87B8-480E-ACAA-33502869F203","watched":true,"length":"60","discovered":true,"airdate":"Sunday","running":true,"name":"Winning Time"},{"status":"Up to Date","service":"Netflix","wanted":true,"id":"ADC58DE1-6E47-418E-8AC0-B9034C1F11C0","watched":true,"length":"30-60","discovered":true,"airdate":"Other","running":true,"name":"Bridgerton"},{"status":"Show Ended","service":"Disney+","wanted":true,"id":"77C815C6-0D79-4AA2-BF58-E9DBFD28E534","watched":false,"length":"60","discovered":true,"airdate":"Wednesday","running":true,"name":"Moon Knight"},{"status":"Show Ended","service":"Apple TV+","wanted":true,"id":"EBE1E7F5-7714-4537-8558-002399FFF93A","watched":true,"length":"60","discovered":true,"airdate":"Friday","running":true,"name":"WeCrashed"},{"status":"Needs Watched","service":"Apple TV+","wanted":true,"id":"797E065C-90E0-47FA-B988-5AA9AAD3E685","watched":false,"length":"60","discovered":true,"airdate":"Other","running":true,"name":"Pachinko"},{"status":"Needs Watched","service":"Apple TV+","wanted":true,"id":"3DF29670-952E-47F1-B7D6-7B5A4BEF8DAC","watched":false,"length":"30-60","discovered":true,"airdate":"Other","running":true,"name":"Slow Horses"},{"status":"Needs Watched","service":"HBO","wanted":true,"id":"4E027D06-4ABB-4E2B-9267-EE6212B4F14A","watched":false,"length":"30-60","discovered":true,"airdate":"Other","running":true,"name":"We Own This City"},{"status":"Currently Airing","service":"HBO","wanted":true,"id":"BA7D41B5-37D0-4205-B3A4-32AAE1A872E6","watched":true,"length":"30","discovered":true,"airdate":"Thursday","running":true,"name":"Made for Love"},{"status":"Needs Watched","service":"Netflix","wanted":true,"id":"2412CDA3-3661-4293-A4CA-18A0E596724B","watched":false,"length":"60","discovered":true,"airdate":"Other","running":true,"name":"Ozark"},{"status":"Needs Watched","service":"HBO","wanted":true,"id":"5A244B74-78CB-4C6C-8F87-8621EECD86E5","watched":false,"length":"60","discovered":true,"airdate":"Other","running":true,"name":"The Staircase"},{"status":"Other","service":"Other","wanted":true,"id":"4F3F9CB1-22EC-4EB0-A935-E1D52BED5C58","watched":false,"length":"<30","discovered":true,"airdate":"Other","running":true,"name":"New Show"}]